setup.cfg
setup.py
jobs_detector/__init__.py
jobs_detector/exceptions.py
jobs_detector/main.py
jobs_detector/settings.py
rmotr_b9_pyp_g1_jobs_detector.egg-info/PKG-INFO
rmotr_b9_pyp_g1_jobs_detector.egg-info/SOURCES.txt
rmotr_b9_pyp_g1_jobs_detector.egg-info/dependency_links.txt
rmotr_b9_pyp_g1_jobs_detector.egg-info/not-zip-safe
rmotr_b9_pyp_g1_jobs_detector.egg-info/top_level.txt