Metadata-Version: 1.0
Name: rmotr-b9-pyp-g1-jobs-detector
Version: 0.0.1
Summary: rmotr.com Group 6 | Jobs Detector
Home-page: https://github.com/StefGou/pyp-w3-gw-jobs-detector/
Author: rmotr.com
Author-email: questions@rmotr.com
License: CC BY-SA 4.0 License
Platform: UNKNOWN
